datasinda/__init__.py
datasinda/admin.py
datasinda/apps.py
datasinda/models.py
datasinda/modulo.py
datasinda/serializers.py
datasinda/tests.py
datasinda/urls.py
datasinda/views.py
datasinda/migrations/__init__.py
datasinda-0.0.1.dist-info/LICENSE
datasinda-0.0.1.dist-info/METADATA
datasinda-0.0.1.dist-info/WHEEL
datasinda-0.0.1.dist-info/top_level.txt
datasinda-0.0.1.dist-info/RECORD
